odoo/addons/sale_stock_prebook_stock_available_to_promise_release/README.rst
odoo/addons/sale_stock_prebook_stock_available_to_promise_release/__init__.py
odoo/addons/sale_stock_prebook_stock_available_to_promise_release/__manifest__.py
odoo/addons/sale_stock_prebook_stock_available_to_promise_release/i18n/it.po
odoo/addons/sale_stock_prebook_stock_available_to_promise_release/i18n/sale_stock_prebook_stock_available_to_promise_release.pot
odoo/addons/sale_stock_prebook_stock_available_to_promise_release/models/__init__.py
odoo/addons/sale_stock_prebook_stock_available_to_promise_release/models/sale_order.py
odoo/addons/sale_stock_prebook_stock_available_to_promise_release/models/sale_order_line.py
odoo/addons/sale_stock_prebook_stock_available_to_promise_release/models/stock_move.py
odoo/addons/sale_stock_prebook_stock_available_to_promise_release/readme/CONTRIBUTORS.rst
odoo/addons/sale_stock_prebook_stock_available_to_promise_release/readme/DESCRIPTION.rst
odoo/addons/sale_stock_prebook_stock_available_to_promise_release/static/description/icon.png
odoo/addons/sale_stock_prebook_stock_available_to_promise_release/static/description/index.html
odoo/addons/sale_stock_prebook_stock_available_to_promise_release/tests/__init__.py
odoo/addons/sale_stock_prebook_stock_available_to_promise_release/tests/test_sale_stock_prebook.py
odoo14_addon_sale_stock_prebook_stock_available_to_promise_release-14.0.1.1.0.dist-info/METADATA
odoo14_addon_sale_stock_prebook_stock_available_to_promise_release-14.0.1.1.0.dist-info/WHEEL
odoo14_addon_sale_stock_prebook_stock_available_to_promise_release-14.0.1.1.0.dist-info/top_level.txt
odoo14_addon_sale_stock_prebook_stock_available_to_promise_release-14.0.1.1.0.dist-info/RECORD
