Metadata-Version: 2.1
Name: odoo14-addon-sale_stock_prebook_stock_available_to_promise_release
Version: 14.0.1.1.0
Summary: Extends the previous available qty to promised with moves of a reservation
Home-page: https://github.com/OCA/sale-prebook
Author: MT Software, Odoo Community Association (OCA)
Author-email: support@odoo-community.org
License: LGPL-3
Classifier: Programming Language :: Python
Classifier: Framework :: Odoo
Classifier: Framework :: Odoo :: 14.0
Classifier: License :: OSI Approved :: GNU Lesser General Public License v3 (LGPLv3)
Requires-Python: >=3.6
Requires-Dist: odoo14-addon-sale-stock-prebook
Requires-Dist: odoo14-addon-stock-available-to-promise-release
Requires-Dist: odoo<14.1dev,>=14.0a
